bsonstream/__init__.py
python_bsonstream-0.1.4.dist-info/LICENSE
python_bsonstream-0.1.4.dist-info/METADATA
python_bsonstream-0.1.4.dist-info/WHEEL
python_bsonstream-0.1.4.dist-info/top_level.txt
python_bsonstream-0.1.4.dist-info/RECORD
