Metadata-Version: 2.1
Name: python-bsonstream
Version: 0.1.4
Summary: UNKNOWN
Home-page: https://github.com/bauman/python-bson-streaming
Maintainer: Dan Bauman
Maintainer-email: dan@bauman.space
License: MIT
Download-URL: https://github.com/bauman/python-bson-streaming/archive/0.1.4.tar.gz
Platform: UNKNOWN
Classifier: License :: OSI Approved :: MIT License
Classifier: Operating System :: OS Independent
Classifier: Programming Language :: Python
Classifier: Programming Language :: Python :: 2
Classifier: Programming Language :: Python :: 3
Requires-Dist: six
Requires-Dist: pymongo
